<mods xmlns="http://www.loc.gov/mods/v3" xmlns:xsi="http://www.w3.org/2001/XMLSchema-instance">
  <titleInfo>
    <title>Yogācāra in autochthoner tibetischer Doxographie unter besonderer Berücksichtigung des Thugs rje sems dpa'i theg pa der Bon-Tradition</title>
  </titleInfo>
  <typeOfResource>text</typeOfResource>
  <genre authority="local">book</genre>
  <genre authority="marcgt">book</genre>
  <name type="personal">
    <namePart type="family">Carstens</namePart>
    <namePart type="given">Carola</namePart>
    <role>
      <roleTerm type="code" authority="marcrelator">aut</roleTerm>
    </role>
  </name>
  <originInfo>
    <place>
      <placeTerm type="text">Hamburg</placeTerm>
    </place>
    <copyrightDate>2006</copyrightDate>
    <issuance>monographic</issuance>
  </originInfo>
</mods>
