<mods xmlns="http://www.loc.gov/mods/v3" xmlns:xsi="http://www.w3.org/2001/XMLSchema-instance">
  <titleInfo>
    <title>Bodhi(sattva)caryāvatāra als Lehrschrift und Vorhaben: Zum Thema Ritual, Religion, Philosophie und Mystik im Buddhismus</title>
  </titleInfo>
  <typeOfResource>text</typeOfResource>
  <genre authority="local">bookSection</genre>
  <name type="personal">
    <namePart type="family">Ruegg</namePart>
    <namePart type="given">David Seyfort</namePart>
    <role>
      <roleTerm type="code" authority="marcrelator">aut</roleTerm>
    </role>
  </name>
  <relatedItem type="host">
    <genre authority="marcgt">book</genre>
    <part>
      <extent unit="pages">
        <start>111</start>
        <end>128</end>
      </extent>
    </part>
    <originInfo>
      <place>
        <placeTerm type="text">Hamburg</placeTerm>
      </place>
      <publisher>Universität Hamburg</publisher>
      <copyrightDate>1999</copyrightDate>
      <issuance>monographic</issuance>
    </originInfo>
    <titleInfo>
      <title>Buddhismus in Geschichte und Gegenwart. Band 3. Śāntidevas "Eintritt in das Leben zur Erleuchtung"</title>
    </titleInfo>
  </relatedItem>
</mods>
