<mods xmlns="http://www.loc.gov/mods/v3" xmlns:xsi="http://www.w3.org/2001/XMLSchema-instance">
  <titleInfo>
    <title>Nāgārjuna and the limits of thought</title>
  </titleInfo>
  <typeOfResource>text</typeOfResource>
  <genre authority="local">journalArticle</genre>
  <name type="personal">
    <namePart type="family">Garfield</namePart>
    <namePart type="given">Jay L.</namePart>
    <role>
      <roleTerm type="code" authority="marcrelator">aut</roleTerm>
    </role>
  </name>
  <name type="personal">
    <namePart type="family">Priest</namePart>
    <namePart type="given">Graham</namePart>
    <role>
      <roleTerm type="code" authority="marcrelator">aut</roleTerm>
    </role>
  </name>
  <relatedItem type="host">
    <genre authority="marcgt">journal</genre>
    <part>
      <detail type="volume">
        <number>53/1</number>
      </detail>
      <extent unit="pages">
        <start>1</start>
        <end>21</end>
      </extent>
    </part>
    <originInfo>
      <dateIssued>2003</dateIssued>
      <issuance>continuing</issuance>
    </originInfo>
    <titleInfo>
      <title>Philosophy East and West</title>
    </titleInfo>
  </relatedItem>
</mods>
