<mods xmlns="http://www.loc.gov/mods/v3" xmlns:xsi="http://www.w3.org/2001/XMLSchema-instance">
  <titleInfo>
    <title>Zu einigen mongolischen historischen Sagen des Kukunoor-Gebietes</title>
  </titleInfo>
  <typeOfResource>text</typeOfResource>
  <genre authority="local">bookSection</genre>
  <name type="personal">
    <namePart type="family">Heissig</namePart>
    <namePart type="given">Walther</namePart>
    <role>
      <roleTerm type="code" authority="marcrelator">aut</roleTerm>
    </role>
  </name>
  <relatedItem type="host">
    <genre authority="marcgt">book</genre>
    <name type="personal">
      <namePart type="family">Steinkellner</namePart>
      <namePart type="given">Ernst</namePart>
      <role>
        <roleTerm type="code" authority="marcrelator">edt</roleTerm>
      </role>
    </name>
    <part>
      <extent unit="pages">
        <start>221</start>
        <end>231</end>
      </extent>
    </part>
    <originInfo>
      <place>
        <placeTerm type="text">Wien</placeTerm>
      </place>
      <publisher>Arbeitskreis für Tibetische und Buddhistische Studien, Universität Wien</publisher>
      <copyrightDate>1991</copyrightDate>
      <issuance>monographic</issuance>
    </originInfo>
    <titleInfo>
      <title>Tibetan History and Language. Studies Dedicated to Uray Géza on his Seventieth Birthday</title>
    </titleInfo>
  </relatedItem>
</mods>
