<mods xmlns="http://www.loc.gov/mods/v3" xmlns:xsi="http://www.w3.org/2001/XMLSchema-instance">
  <titleInfo>
    <title>Spa-tshab nyi-ma-grags and the introduction of Prāsaṅgika Madhyamaka into Tibet</title>
  </titleInfo>
  <typeOfResource>text</typeOfResource>
  <genre authority="local">bookSection</genre>
  <name type="personal">
    <namePart type="family">Lang</namePart>
    <namePart type="given">Karen</namePart>
    <role>
      <roleTerm type="code" authority="marcrelator">aut</roleTerm>
    </role>
  </name>
  <relatedItem type="host">
    <genre authority="marcgt">book</genre>
    <name type="personal">
      <namePart type="family">Epstein</namePart>
      <namePart type="given">L.</namePart>
      <role>
        <roleTerm type="code" authority="marcrelator">edt</roleTerm>
      </role>
    </name>
    <name type="personal">
      <namePart type="family">Sherburne</namePart>
      <namePart type="given">R.</namePart>
      <role>
        <roleTerm type="code" authority="marcrelator">edt</roleTerm>
      </role>
    </name>
    <part>
      <extent unit="pages">
        <start>127</start>
        <end>141</end>
      </extent>
    </part>
    <originInfo>
      <place>
        <placeTerm type="text">New York</placeTerm>
      </place>
      <publisher>The Edwin Mellen Press</publisher>
      <copyrightDate>1990</copyrightDate>
      <issuance>monographic</issuance>
    </originInfo>
    <titleInfo>
      <title>Reflections on Tibetan Culture: Essays in Memory of Turrell V. Wylie (Studies in Asian Thought and Religion)</title>
    </titleInfo>
  </relatedItem>
</mods>
