<mods xmlns="http://www.loc.gov/mods/v3" xmlns:xsi="http://www.w3.org/2001/XMLSchema-instance">
  <titleInfo>
    <title>1) A. Foucher: Notes sur la géographie ancienne du Gandhāra (1901); 2) Jas. Burgess: Buddhist Art in India (1902); 3) V. A. Smith: Açoka the buddhist emperor of India (1901): 4) S. Lévi: Quelques termes employés dans des Inscriptions des Kṣatrapas (1902); 5) E. Washburn Hopkins: The Great Epic of India (1901); Kaccayana's Pali Grammar (1901); 7) G. A. van den Berg van Eysinga: Indische invloeden op oude christelijke verhalen (1901); F. Aiken: The Dhamma of Gotama the Buddha and the Gospel of Jesus Christ (1900); 8) S. Kennedy: Buddhist Gnosticism (1902)</title>
  </titleInfo>
  <typeOfResource>text</typeOfResource>
  <genre authority="local">journalArticle</genre>
  <name type="personal">
    <namePart type="family">Poussin</namePart>
    <namePart type="given">Louis de la Vallée</namePart>
    <role>
      <roleTerm type="code" authority="marcrelator">aut</roleTerm>
    </role>
  </name>
  <relatedItem type="host">
    <genre authority="marcgt">journal</genre>
    <part>
      <detail type="volume">
        <number>n.s. 3</number>
      </detail>
      <extent unit="pages">
        <start>267</start>
        <end>273</end>
      </extent>
    </part>
    <originInfo>
      <dateIssued>1902</dateIssued>
      <issuance>continuing</issuance>
    </originInfo>
    <titleInfo>
      <title>Le Muséon</title>
    </titleInfo>
  </relatedItem>
</mods>
