<mods xmlns="http://www.loc.gov/mods/v3" xmlns:xsi="http://www.w3.org/2001/XMLSchema-instance">
  <titleInfo>
    <title>Madhyamakāloka no ichijō-shisō - ichijō-shisō no kenkyū (1) [The ekayāna theory of the Madhyamakāloka - Studies on the ekayāna theory (1)]</title>
  </titleInfo>
  <typeOfResource>text</typeOfResource>
  <genre authority="local">journalArticle</genre>
  <name type="personal">
    <namePart type="family">Matsumoto</namePart>
    <namePart type="given">Shirō</namePart>
    <role>
      <roleTerm type="code" authority="marcrelator">aut</roleTerm>
    </role>
  </name>
  <relatedItem type="host">
    <genre authority="marcgt">journal</genre>
    <part>
      <detail type="volume">
        <number>14</number>
      </detail>
      <extent unit="pages">
        <start>301</start>
        <end>255</end>
      </extent>
    </part>
    <originInfo>
      <dateIssued>1982</dateIssued>
      <issuance>continuing</issuance>
    </originInfo>
    <titleInfo>
      <title>Kenkyūin Kenkyūsei Kenkyūkiyō [Journal of the Sōtō Sect Research Fellows]</title>
    </titleInfo>
  </relatedItem>
</mods>
