<mods xmlns="http://www.loc.gov/mods/v3" xmlns:xsi="http://www.w3.org/2001/XMLSchema-instance">
  <titleInfo>
    <title>Jñānagarbha’s Commentary on the Distinction between the Two Truths</title>
  </titleInfo>
  <typeOfResource>text</typeOfResource>
  <genre authority="local">book</genre>
  <genre authority="marcgt">book</genre>
  <name type="personal">
    <namePart type="family">Eckel</namePart>
    <namePart type="given">Malcolm David</namePart>
    <role>
      <roleTerm type="code" authority="marcrelator">aut</roleTerm>
    </role>
  </name>
  <originInfo>
    <publisher>SUNY</publisher>
    <copyrightDate>1987</copyrightDate>
    <issuance>monographic</issuance>
  </originInfo>
</mods>
