<mods xmlns="http://www.loc.gov/mods/v3" xmlns:xsi="http://www.w3.org/2001/XMLSchema-instance">
  <titleInfo>
    <title>Das Saptamaithunasaṃyuktasūtra, ein Sūtra des Ekottarikāgama</title>
  </titleInfo>
  <typeOfResource>text</typeOfResource>
  <genre authority="local">bookSection</genre>
  <name type="personal">
    <namePart type="family">Hahn</namePart>
    <namePart type="given">Michael</namePart>
    <role>
      <roleTerm type="code" authority="marcrelator">aut</roleTerm>
    </role>
  </name>
  <relatedItem type="host">
    <genre authority="marcgt">book</genre>
    <originInfo>
      <place>
        <placeTerm type="text">Berlin</placeTerm>
      </place>
      <copyrightDate>1977</copyrightDate>
      <issuance>monographic</issuance>
    </originInfo>
    <titleInfo>
      <title>Beiträge zur Studienforschung. Ernst Waldschmidt zum 80. Geburtstag gewidmet. (Veröffentlichungen des Museums für Indische Kunst Berlin, Band 4)</title>
    </titleInfo>
  </relatedItem>
</mods>
