<mods xmlns="http://www.loc.gov/mods/v3" xmlns:xsi="http://www.w3.org/2001/XMLSchema-instance">
  <titleInfo>
    <title>Review: E. Obermiller (ed.), Prajñā-pāramitā-ratna-guṇa-saṃcaya-gāthā. Sanskrit and Tibetan text edited by E. Obermiller. Photomechanic reprint with a Sanskrit-Tibetan-English-index by Edward Conze. 's-Gravenhage, Mouton &amp; Co, 1960 (Indo-Iranian Reprints edited by the Editorial Board of the Indo-Iranian Journal 5).</title>
  </titleInfo>
  <typeOfResource>text</typeOfResource>
  <genre authority="local">journalArticle</genre>
  <name type="personal">
    <namePart type="family">Meisezahl</namePart>
    <namePart type="given">R. O.</namePart>
    <role>
      <roleTerm type="code" authority="marcrelator">aut</roleTerm>
    </role>
  </name>
  <relatedItem type="host">
    <genre authority="marcgt">journal</genre>
    <part>
      <detail type="volume">
        <number>17</number>
      </detail>
      <extent unit="pages">
        <start>289</start>
        <end>301</end>
      </extent>
    </part>
    <originInfo>
      <dateIssued>1964</dateIssued>
      <issuance>continuing</issuance>
    </originInfo>
    <titleInfo>
      <title>Oriens</title>
    </titleInfo>
  </relatedItem>
</mods>
