<mods xmlns="http://www.loc.gov/mods/v3" xmlns:xsi="http://www.w3.org/2001/XMLSchema-instance">
  <titleInfo>
    <title>Further Remarks on the Compound avinābhāvaniyama in the Early Dharmakīrti</title>
  </titleInfo>
  <typeOfResource>text</typeOfResource>
  <genre authority="local">journalArticle</genre>
  <name type="personal">
    <namePart type="family">Steinkellner</namePart>
    <namePart type="given">Ernst</namePart>
    <role>
      <roleTerm type="code" authority="marcrelator">aut</roleTerm>
    </role>
  </name>
  <relatedItem type="host">
    <genre authority="marcgt">journal</genre>
    <part>
      <detail type="volume">
        <number>51</number>
      </detail>
      <extent unit="pages">
        <start>193</start>
        <end>205</end>
      </extent>
    </part>
    <originInfo>
      <dateIssued>2007/2008</dateIssued>
      <issuance>continuing</issuance>
    </originInfo>
    <titleInfo>
      <title>WZKS</title>
    </titleInfo>
  </relatedItem>
</mods>
