<mods xmlns="http://www.loc.gov/mods/v3" xmlns:xsi="http://www.w3.org/2001/XMLSchema-instance">
  <titleInfo>
    <title>Reviews: (1) Biography of Dharmasvāmin (Chag lo-tsa-ba Chos-rje-dpal). A Tibetan Monk Pilgrim. Original Tibetan text deciphered and translated by G. Roerich. With a historical and critical introduction by A.S. Altekar. (2) Abhidharmadīpa with Vibhāṣāprabhāvṛtti, critically edited with notes and introduction by P.S. Jaini</title>
  </titleInfo>
  <typeOfResource>text</typeOfResource>
  <genre authority="local">journalArticle</genre>
  <name type="personal">
    <namePart type="family">Jong</namePart>
    <namePart type="given">J. W. De</namePart>
    <role>
      <roleTerm type="code" authority="marcrelator">aut</roleTerm>
    </role>
  </name>
  <relatedItem type="host">
    <genre authority="marcgt">journal</genre>
    <part>
      <detail type="volume">
        <number>6/2</number>
      </detail>
      <extent unit="pages">
        <start>167</start>
        <end>175</end>
      </extent>
    </part>
    <originInfo>
      <dateIssued>1962</dateIssued>
      <issuance>continuing</issuance>
    </originInfo>
    <titleInfo>
      <title>IIJ</title>
    </titleInfo>
  </relatedItem>
</mods>
