<mods xmlns="http://www.loc.gov/mods/v3" xmlns:xsi="http://www.w3.org/2001/XMLSchema-instance">
  <titleInfo>
    <title>The Way We Trust Now: the Authority of Science and the Character of the Scientist</title>
  </titleInfo>
  <typeOfResource>text</typeOfResource>
  <genre authority="local">bookSection</genre>
  <name type="personal">
    <namePart type="family">Shapin</namePart>
    <namePart type="given">Steve</namePart>
    <role>
      <roleTerm type="code" authority="marcrelator">aut</roleTerm>
    </role>
  </name>
  <relatedItem type="host">
    <genre authority="marcgt">book</genre>
    <name type="personal">
      <namePart type="family">Council</namePart>
      <namePart type="given">The British</namePart>
      <role>
        <roleTerm type="code" authority="marcrelator">edt</roleTerm>
      </role>
    </name>
    <part>
      <extent unit="pages">
        <start>42</start>
        <end>63</end>
      </extent>
    </part>
    <originInfo>
      <place>
        <placeTerm type="text">London</placeTerm>
      </place>
      <copyrightDate>2004</copyrightDate>
      <issuance>monographic</issuance>
    </originInfo>
    <titleInfo>
      <title>Trust me, I'm a Scientist (Birthday Counterpoints)</title>
    </titleInfo>
  </relatedItem>
</mods>
