<mods xmlns="http://www.loc.gov/mods/v3" xmlns:xsi="http://www.w3.org/2001/XMLSchema-instance">
  <titleInfo>
    <title>Vergleiche als Stilmittel im Gesar-Epos</title>
  </titleInfo>
  <typeOfResource>text</typeOfResource>
  <genre authority="local">bookSection</genre>
  <name type="personal">
    <namePart type="family">Kaschewsky</namePart>
    <namePart type="given">Rudolf</namePart>
    <role>
      <roleTerm type="code" authority="marcrelator">aut</roleTerm>
    </role>
  </name>
  <relatedItem type="host">
    <genre authority="marcgt">book</genre>
    <name type="personal">
      <namePart type="family">Heissig</namePart>
      <namePart type="given">Walther</namePart>
      <role>
        <roleTerm type="code" authority="marcrelator">edt</roleTerm>
      </role>
    </name>
    <part>
      <extent unit="pages">
        <start>600</start>
        <end>612</end>
      </extent>
    </part>
    <originInfo>
      <place>
        <placeTerm type="text">Wiesbaden</placeTerm>
      </place>
      <publisher>Otto Harrassowitz</publisher>
      <copyrightDate>1986</copyrightDate>
      <issuance>monographic</issuance>
    </originInfo>
    <titleInfo>
      <title>Fragen der mongolischen Heldendichtung Teil III. Vorträge des 4. Epensymposiums des Sonderforschungsbereichs 12, Bonn 1983</title>
    </titleInfo>
  </relatedItem>
</mods>
