<mods xmlns="http://www.loc.gov/mods/v3" xmlns:xsi="http://www.w3.org/2001/XMLSchema-instance">
  <titleInfo>
    <title>The 'Great Debate' of bSam yas - Construction and Deconstruction of a Tibetan Buddhist Myth</title>
  </titleInfo>
  <typeOfResource>text</typeOfResource>
  <genre authority="local">journalArticle</genre>
  <name type="personal">
    <namePart type="family">Bretfeld</namePart>
    <namePart type="given">Sven</namePart>
    <role>
      <roleTerm type="code" authority="marcrelator">aut</roleTerm>
    </role>
  </name>
  <relatedItem type="host">
    <genre authority="marcgt">journal</genre>
    <part>
      <detail type="volume">
        <number>58/1</number>
      </detail>
      <extent unit="pages">
        <start>15</start>
        <end>56</end>
      </extent>
    </part>
    <originInfo>
      <dateIssued>2004</dateIssued>
      <issuance>continuing</issuance>
    </originInfo>
    <titleInfo>
      <title>Asiatische Studien/Etudes Asiatiques</title>
    </titleInfo>
  </relatedItem>
</mods>
