<mods xmlns="http://www.loc.gov/mods/v3" xmlns:xsi="http://www.w3.org/2001/XMLSchema-instance">
  <titleInfo>
    <title>Studies on Bhartṛhari, 7: Grammar as the Door to Liberation</title>
  </titleInfo>
  <typeOfResource>text</typeOfResource>
  <genre authority="local">journalArticle</genre>
  <name type="personal">
    <namePart type="family">Bronkhorst</namePart>
    <namePart type="given">Johannes</namePart>
    <role>
      <roleTerm type="code" authority="marcrelator">aut</roleTerm>
    </role>
  </name>
  <relatedItem type="host">
    <genre authority="marcgt">journal</genre>
    <part>
      <detail type="volume">
        <number>76</number>
      </detail>
      <extent unit="pages">
        <start>97</start>
        <end>106</end>
      </extent>
    </part>
    <originInfo>
      <dateIssued>1995</dateIssued>
      <issuance>continuing</issuance>
    </originInfo>
    <titleInfo>
      <title>Annals of BORI</title>
    </titleInfo>
  </relatedItem>
</mods>
