<mods xmlns="http://www.loc.gov/mods/v3" xmlns:xsi="http://www.w3.org/2001/XMLSchema-instance">
  <titleInfo>
    <title>Cultural Preconditions for Development: Some Asian Experiences</title>
  </titleInfo>
  <typeOfResource>text</typeOfResource>
  <genre authority="local">journalArticle</genre>
  <name type="personal">
    <namePart type="family">Norbu</namePart>
    <namePart type="given">Dawa</namePart>
    <role>
      <roleTerm type="code" authority="marcrelator">aut</roleTerm>
    </role>
  </name>
  <relatedItem type="host">
    <genre authority="marcgt">journal</genre>
    <part>
      <detail type="volume">
        <number>1/2</number>
      </detail>
      <extent unit="pages">
        <start>275</start>
        <end>286</end>
      </extent>
    </part>
    <originInfo>
      <dateIssued>1994</dateIssued>
      <issuance>continuing</issuance>
    </originInfo>
    <titleInfo>
      <title>South Asian Survey</title>
    </titleInfo>
  </relatedItem>
</mods>
