<mods xmlns="http://www.loc.gov/mods/v3" xmlns:xsi="http://www.w3.org/2001/XMLSchema-instance">
  <titleInfo>
    <title>A History of Classical Poetry - Sanskrit - Pāli - Prakrit - A History of Indian Literature Vol. 3/1</title>
  </titleInfo>
  <typeOfResource>text</typeOfResource>
  <genre authority="local">book</genre>
  <genre authority="marcgt">book</genre>
  <name type="personal">
    <namePart type="family">Lienhard</namePart>
    <namePart type="given">Siegfried</namePart>
    <role>
      <roleTerm type="code" authority="marcrelator">aut</roleTerm>
    </role>
  </name>
  <originInfo>
    <place>
      <placeTerm type="text">Wiesbaden</placeTerm>
    </place>
    <publisher>Otto Harrassowitz</publisher>
    <copyrightDate>1984</copyrightDate>
    <issuance>monographic</issuance>
  </originInfo>
</mods>
