<mods xmlns="http://www.loc.gov/mods/v3" xmlns:xsi="http://www.w3.org/2001/XMLSchema-instance">
  <titleInfo>
    <title>Review of: L’Archive des origines: Sanskrit, philologie, anthropologie dans l’Allemagne du XIXe siècle. Von Pascale Rabault-Feuerhahn. Paris: Editions du Cerf, 2008. 484 pp. ISBN: 978-2-204-08559-5.</title>
  </titleInfo>
  <typeOfResource>text</typeOfResource>
  <genre authority="local">journalArticle</genre>
  <name type="personal">
    <namePart type="family">Trautmann-Waller</namePart>
    <namePart type="given">Céline</namePart>
    <role>
      <roleTerm type="code" authority="marcrelator">aut</roleTerm>
    </role>
  </name>
  <relatedItem type="host">
    <genre authority="marcgt">journal</genre>
    <part>
      <detail type="volume">
        <number>37</number>
      </detail>
    </part>
    <originInfo>
      <dateIssued>2010</dateIssued>
      <issuance>continuing</issuance>
    </originInfo>
    <titleInfo>
      <title>Historiographia linguistica</title>
    </titleInfo>
  </relatedItem>
</mods>
