<mods xmlns="http://www.loc.gov/mods/v3" xmlns:xsi="http://www.w3.org/2001/XMLSchema-instance">
  <titleInfo>
    <title>Buddhist Meditation. An anthology of texts from the Pali Canon</title>
  </titleInfo>
  <typeOfResource>text</typeOfResource>
  <genre authority="local">book</genre>
  <genre authority="marcgt">book</genre>
  <name type="personal">
    <namePart type="family">Shaw</namePart>
    <namePart type="given">Sarah</namePart>
    <role>
      <roleTerm type="code" authority="marcrelator">aut</roleTerm>
    </role>
  </name>
  <originInfo>
    <publisher>RoutledgeCurzon</publisher>
    <copyrightDate>2006</copyrightDate>
    <issuance>monographic</issuance>
  </originInfo>
</mods>
