<mods xmlns="http://www.loc.gov/mods/v3" xmlns:xsi="http://www.w3.org/2001/XMLSchema-instance">
  <titleInfo>
    <title>The Buddhist World of Southeast Asia</title>
  </titleInfo>
  <typeOfResource>text</typeOfResource>
  <genre authority="local">book</genre>
  <genre authority="marcgt">book</genre>
  <name type="personal">
    <namePart type="family">Swearer</namePart>
    <namePart type="given">Donald K.</namePart>
    <role>
      <roleTerm type="code" authority="marcrelator">aut</roleTerm>
    </role>
  </name>
  <originInfo>
    <place>
      <placeTerm type="text">Albany</placeTerm>
    </place>
    <publisher>State University of New York Press</publisher>
    <copyrightDate>2010</copyrightDate>
    <issuance>monographic</issuance>
  </originInfo>
</mods>
