<mods xmlns="http://www.loc.gov/mods/v3" xmlns:xsi="http://www.w3.org/2001/XMLSchema-instance">
  <titleInfo>
    <title>The Samādhi of Direct Encounter with the Buddhas of the Present. An Annotated English Translation of the Tibetan Version of the Pratyutpanna-Buddha-Saṃmukhāvasthita-Samādhi-Sūtra with Several Appendices relating to the History of the Text</title>
  </titleInfo>
  <typeOfResource>text</typeOfResource>
  <genre authority="local">book</genre>
  <genre authority="marcgt">book</genre>
  <name type="personal">
    <namePart type="family">Harrison</namePart>
    <namePart type="given">Paul</namePart>
    <role>
      <roleTerm type="code" authority="marcrelator">aut</roleTerm>
    </role>
  </name>
  <originInfo>
    <place>
      <placeTerm type="text">Tokyo</placeTerm>
    </place>
    <publisher>The International Institute for Buddhist Studies</publisher>
    <copyrightDate>1990</copyrightDate>
    <issuance>monographic</issuance>
  </originInfo>
</mods>
