<mods xmlns="http://www.loc.gov/mods/v3" xmlns:xsi="http://www.w3.org/2001/XMLSchema-instance">
  <titleInfo>
    <title>Architecture: Buddhist Monasteries in Southern Asia</title>
  </titleInfo>
  <typeOfResource>text</typeOfResource>
  <genre authority="local">bookSection</genre>
  <name type="personal">
    <namePart type="family">Huntington</namePart>
    <namePart type="given">John C.</namePart>
    <role>
      <roleTerm type="code" authority="marcrelator">aut</roleTerm>
    </role>
  </name>
  <name type="personal">
    <namePart type="family">Chandrasekhar</namePart>
    <namePart type="given">Chaya</namePart>
    <role>
      <roleTerm type="code" authority="marcrelator">aut</roleTerm>
    </role>
  </name>
  <relatedItem type="host">
    <genre authority="marcgt">book</genre>
    <name type="personal">
      <namePart type="family">Johnston</namePart>
      <namePart type="given">William M.</namePart>
      <role>
        <roleTerm type="code" authority="marcrelator">edt</roleTerm>
      </role>
    </name>
    <part>
      <extent unit="pages">
        <start>55</start>
        <end>66</end>
      </extent>
    </part>
    <originInfo>
      <publisher>Fitzroy Dearborn Publishers</publisher>
      <copyrightDate>2000</copyrightDate>
      <issuance>monographic</issuance>
    </originInfo>
    <titleInfo>
      <title>Encyclopedia of Monasticism, Volume I, A-L</title>
    </titleInfo>
  </relatedItem>
</mods>
