<mods xmlns="http://www.loc.gov/mods/v3" xmlns:xsi="http://www.w3.org/2001/XMLSchema-instance">
  <titleInfo>
    <title>English in Tibet, Tibet in English: Self-Presentation in Tibet and the Diaspora</title>
  </titleInfo>
  <typeOfResource>text</typeOfResource>
  <genre authority="local">book</genre>
  <genre authority="marcgt">book</genre>
  <name type="personal">
    <namePart type="family">McMillian</namePart>
    <namePart type="given">Laurie Hovell</namePart>
    <role>
      <roleTerm type="code" authority="marcrelator">aut</roleTerm>
    </role>
  </name>
  <originInfo>
    <publisher>Palgrave</publisher>
    <copyrightDate>2001</copyrightDate>
    <issuance>monographic</issuance>
  </originInfo>
</mods>
