<mods xmlns="http://www.loc.gov/mods/v3" xmlns:xsi="http://www.w3.org/2001/XMLSchema-instance">
  <titleInfo>
    <title>The Soka Gakkai: Buddhism and the Creation of a Harmonious and Peaceful Society</title>
  </titleInfo>
  <typeOfResource>text</typeOfResource>
  <genre authority="local">bookSection</genre>
  <name type="personal">
    <namePart type="family">Metraux</namePart>
    <namePart type="given">Daniel A.</namePart>
    <role>
      <roleTerm type="code" authority="marcrelator">aut</roleTerm>
    </role>
  </name>
  <relatedItem type="host">
    <genre authority="marcgt">book</genre>
    <name type="personal">
      <namePart type="family">Queen</namePart>
      <namePart type="given">Christopher S.</namePart>
      <role>
        <roleTerm type="code" authority="marcrelator">edt</roleTerm>
      </role>
    </name>
    <name type="personal">
      <namePart type="family">King</namePart>
      <namePart type="given">Sallie B.</namePart>
      <role>
        <roleTerm type="code" authority="marcrelator">edt</roleTerm>
      </role>
    </name>
    <part>
      <extent unit="pages">
        <start>365</start>
        <end>400</end>
      </extent>
    </part>
    <originInfo>
      <place>
        <placeTerm type="text">New York</placeTerm>
      </place>
      <publisher>State University of New York Press</publisher>
      <copyrightDate>1996</copyrightDate>
      <issuance>monographic</issuance>
    </originInfo>
    <titleInfo>
      <title>Engaged Buddhism - Buddhist Liberation Movements in Asia</title>
    </titleInfo>
  </relatedItem>
</mods>
