<mods xmlns="http://www.loc.gov/mods/v3" xmlns:xsi="http://www.w3.org/2001/XMLSchema-instance">
  <titleInfo>
    <title>Indologies: German and Other</title>
  </titleInfo>
  <typeOfResource>text</typeOfResource>
  <genre authority="local">bookSection</genre>
  <name type="personal">
    <namePart type="family">Goldman</namePart>
    <namePart type="given">Robert P.</namePart>
    <role>
      <roleTerm type="code" authority="marcrelator">aut</roleTerm>
    </role>
  </name>
  <relatedItem type="host">
    <genre authority="marcgt">book</genre>
    <name type="personal">
      <namePart type="family">McGetchin</namePart>
      <namePart type="given">Douglas T.</namePart>
      <role>
        <roleTerm type="code" authority="marcrelator">edt</roleTerm>
      </role>
    </name>
    <name type="personal">
      <namePart type="family">Park</namePart>
      <namePart type="given">Peter K. J.</namePart>
      <role>
        <roleTerm type="code" authority="marcrelator">edt</roleTerm>
      </role>
    </name>
    <name type="personal">
      <namePart type="family">SarDesai</namePart>
      <namePart type="given">Damodar</namePart>
      <role>
        <roleTerm type="code" authority="marcrelator">edt</roleTerm>
      </role>
    </name>
    <part>
      <extent unit="pages">
        <start>27</start>
        <end>40</end>
      </extent>
    </part>
    <originInfo>
      <place>
        <placeTerm type="text">New Delhi</placeTerm>
      </place>
      <publisher>Manohar</publisher>
      <copyrightDate>2004</copyrightDate>
      <issuance>monographic</issuance>
    </originInfo>
    <titleInfo>
      <title>Sanskrit and 'Orientalism'. Indology and Comparative Linguistics in Germany, 1750-1958</title>
    </titleInfo>
  </relatedItem>
</mods>
